arcade_exa_api/__init__.py
arcade_exa_api/moar/Exa.json
arcade_exa_api/moar/openapi.json
arcade_exa_api/tools/__init__.py
arcade_exa_api/tools/request_body_schemas.py
arcade_exa_api/wrapper_tools/CancelEnrichmentProcess.json
arcade_exa_api/wrapper_tools/CancelRunningSearch.json
arcade_exa_api/wrapper_tools/CancelWebsetOperations.json
arcade_exa_api/wrapper_tools/CreateDataImport.json
arcade_exa_api/wrapper_tools/CreateMonitorForWebsets.json
arcade_exa_api/wrapper_tools/CreateResearchRequest.json
arcade_exa_api/wrapper_tools/CreateWebhookForNotifications.json
arcade_exa_api/wrapper_tools/CreateWebset.json
arcade_exa_api/wrapper_tools/CreateWebsetEnrichment.json
arcade_exa_api/wrapper_tools/CreateWebsetSearch.json
arcade_exa_api/wrapper_tools/DeleteEnrichment.json
arcade_exa_api/wrapper_tools/DeleteImport.json
arcade_exa_api/wrapper_tools/DeleteMonitor.json
arcade_exa_api/wrapper_tools/DeleteWebset.json
arcade_exa_api/wrapper_tools/DeleteWebsetItem.json
arcade_exa_api/wrapper_tools/FindSimilarLinks.json
arcade_exa_api/wrapper_tools/GenerateAnswerSummary.json
arcade_exa_api/wrapper_tools/GetContentDetails.json
arcade_exa_api/wrapper_tools/GetEnrichmentDetails.json
arcade_exa_api/wrapper_tools/GetEventById.json
arcade_exa_api/wrapper_tools/GetResearchById.json
arcade_exa_api/wrapper_tools/GetSearchById.json
arcade_exa_api/wrapper_tools/GetSpecificImport.json
arcade_exa_api/wrapper_tools/GetSpecificMonitor.json
arcade_exa_api/wrapper_tools/GetSpecificMonitorRun.json
arcade_exa_api/wrapper_tools/GetWebhookInfo.json
arcade_exa_api/wrapper_tools/GetWebhooksList.json
arcade_exa_api/wrapper_tools/GetWebsetDetails.json
arcade_exa_api/wrapper_tools/GetWebsetItem.json
arcade_exa_api/wrapper_tools/ListImports.json
arcade_exa_api/wrapper_tools/ListMonitorRuns.json
arcade_exa_api/wrapper_tools/ListResearchRequests.json
arcade_exa_api/wrapper_tools/ListSystemEvents.json
arcade_exa_api/wrapper_tools/ListWebhookAttempts.json
arcade_exa_api/wrapper_tools/ListWebsetItems.json
arcade_exa_api-2.0.0.dist-info/METADATA
arcade_exa_api-2.0.0.dist-info/WHEEL
arcade_exa_api-2.0.0.dist-info/entry_points.txt
arcade_exa_api-2.0.0.dist-info/licenses/LICENSE
arcade_exa_api-2.0.0.dist-info/RECORD
